scorer_to_usebio/__init__.py
scorer_to_usebio/__main__.py
scorer_to_usebio/convert.py
scorer_to_usebio/qt.py
scorer_to_usebio-0.3.dist-info/DESCRIPTION.rst
scorer_to_usebio-0.3.dist-info/METADATA
scorer_to_usebio-0.3.dist-info/RECORD
scorer_to_usebio-0.3.dist-info/WHEEL
scorer_to_usebio-0.3.dist-info/entry_points.txt
scorer_to_usebio-0.3.dist-info/metadata.json
scorer_to_usebio-0.3.dist-info/top_level.txt
scorer_to_usebio-0.3.dist-info/zip-safe
