Metadata-Version: 2.0
Name: scorer-to-usebio
Version: 0.3
Summary: Converts from Bridge NZ Scorer format to USEBIO 1.2
Home-page: https://github.com/duaneg/scorer-to-usebio
Author: Duane Griffin
Author-email: duaneg@dghda.com
License: GNU AGPLv3+
Platform: UNKNOWN
